odoo8_addon_l10n_fr_chorus_account-8.0.1.0.0.99.dev5-py2.7-nspkg.pth
odoo8_addon_l10n_fr_chorus_account-8.0.1.0.0.99.dev5.dist-info/METADATA
odoo8_addon_l10n_fr_chorus_account-8.0.1.0.0.99.dev5.dist-info/RECORD
odoo8_addon_l10n_fr_chorus_account-8.0.1.0.0.99.dev5.dist-info/WHEEL
odoo8_addon_l10n_fr_chorus_account-8.0.1.0.0.99.dev5.dist-info/namespace_packages.txt
odoo8_addon_l10n_fr_chorus_account-8.0.1.0.0.99.dev5.dist-info/top_level.txt
odoo_addons/l10n_fr_chorus_account/README.rst
odoo_addons/l10n_fr_chorus_account/__init__.py
odoo_addons/l10n_fr_chorus_account/__openerp__.py
odoo_addons/l10n_fr_chorus_account/data/transmit_method.xml
odoo_addons/l10n_fr_chorus_account/demo/demo.xml
odoo_addons/l10n_fr_chorus_account/i18n/l10n_fr_chorus_account.pot
odoo_addons/l10n_fr_chorus_account/models/__init__.py
odoo_addons/l10n_fr_chorus_account/models/account_config_settings.py
odoo_addons/l10n_fr_chorus_account/models/account_invoice.py
odoo_addons/l10n_fr_chorus_account/models/company.py
odoo_addons/l10n_fr_chorus_account/models/partner.py
odoo_addons/l10n_fr_chorus_account/models/public_market.py
odoo_addons/l10n_fr_chorus_account/security/ir.model.access.csv
odoo_addons/l10n_fr_chorus_account/security/public_market_security.xml
odoo_addons/l10n_fr_chorus_account/static/description/icon.png
odoo_addons/l10n_fr_chorus_account/views/account_config_settings.xml
odoo_addons/l10n_fr_chorus_account/views/account_invoice.xml
odoo_addons/l10n_fr_chorus_account/views/partner.xml
odoo_addons/l10n_fr_chorus_account/views/public_market.xml
