Metadata-Version: 2.1
Name: odoo8-addon-l10n-fr-chorus-account
Version: 8.0.1.0.0.99.dev5
Summary: Generate Chorus-compliant e-invoices
Home-page: http://www.akretion.com
Author: Akretion,Odoo Community Association (OCA)
Author-email: support@odoo-community.org
License: AGPL-3
Platform: UNKNOWN
Classifier: Programming Language :: Python
Classifier: Framework :: Odoo
Classifier: License :: OSI Approved :: GNU Affero General Public License v3
Requires-Python: ~=2.7
Requires-Dist: odoo8-addon-account-invoice-transmit-method
Requires-Dist: odoo8-addon-l10n-fr-siret
Requires-Dist: odoo (<9.0a,>=8.0a)
